{
  "pageLayoutID": "421564725797584897",
  "namespaceID": "409824987081211905",
  "moduleID": "421363471985147905",
  "pageID": "421394352531570689",
  "parentID": "0",
  "handle": "Start",
  "primary": false,
  "weight": 5,
  "meta": {
    "title": "Start",
    "description": "",
    "script": "",
    "scriptEnabled": false
  },
  "config": {
    "visibility": {
      "expression": "isPop"
    },
    "buttons": {
      "new": {
        "enabled": false,
        "label": "",
        "actionID": "",
        "params": null
      },
      "edit": {
        "enabled": false,
        "label": "",
        "actionID": "",
        "params": null
      },
      "submit": {
        "enabled": true,
        "label": "",
        "actionID": "",
        "params": null
      },
      "delete": {
        "enabled": false,
        "label": "",
        "actionID": "",
        "params": null
      },
      "clone": {
        "enabled": false,
        "label": "",
        "actionID": "",
        "params": null
      },
      "back": {
        "enabled": true,
        "label": "",
        "actionID": "",
        "params": null
      }
    },
    "useTitle": true
  },
  "blocks": [
    {
      "blockID": "9",
      "xywh": [
        0,
        0,
        20,
        15
      ],
      "meta": {
        "hidden": false,
        "tempID": "tempID-bnirzn7e8fpm4tl7c1v"
      }
    }
  ],
  "ownedBy": "0",
  "createdAt": "2024-12-18T07:43:46Z",
  "updatedAt": "2026-03-02T19:12:29Z",
  "layoutID": "421564725797584897"
}