{
  "pageLayoutID": "412265616993419265",
  "namespaceID": "409824987081211905",
  "moduleID": "0",
  "pageID": "412265613033996289",
  "parentID": "0",
  "handle": "primary",
  "primary": false,
  "weight": 1,
  "meta": {
    "title": "Ticket Management",
    "description": "",
    "script": "",
    "scriptEnabled": false
  },
  "config": {
    "visibility": {
      "expression": ""
    },
    "buttons": {
      "new": {
        "enabled": true,
        "label": "",
        "actionID": "",
        "params": null
      },
      "edit": {
        "enabled": true,
        "label": "",
        "actionID": "",
        "params": null
      },
      "submit": {
        "enabled": true,
        "label": "",
        "actionID": "",
        "params": null
      },
      "delete": {
        "enabled": true,
        "label": "",
        "actionID": "",
        "params": null
      },
      "clone": {
        "enabled": true,
        "label": "",
        "actionID": "",
        "params": null
      },
      "back": {
        "enabled": true,
        "label": "",
        "actionID": "",
        "params": null
      }
    },
    "useTitle": false
  },
  "blocks": [
    {
      "blockID": "1",
      "xywh": [
        0,
        0,
        48,
        82
      ],
      "meta": {
        "hidden": false,
        "tempID": "tempID-mns49xt88lam29ti18f"
      }
    }
  ],
  "ownedBy": "0",
  "createdAt": "2024-10-15T02:22:01Z",
  "updatedAt": "2026-03-02T19:12:29Z",
  "layoutID": "412265616993419265"
}